call_function_with_timeout/__init__.py
call_function_with_timeout/test_timeout.py
call_function_with_timeout/timeout.py
call_function_with_timeout-1.1.1.dist-info/LICENSE
call_function_with_timeout-1.1.1.dist-info/METADATA
call_function_with_timeout-1.1.1.dist-info/WHEEL
call_function_with_timeout-1.1.1.dist-info/top_level.txt
call_function_with_timeout-1.1.1.dist-info/RECORD
