Metadata-Version: 2.1
Name: call-function-with-timeout
Version: 1.1.1
Summary: Python Call function with timeouts
Home-page: https://github.com/yang445786754/call_function_with_timeout
Author: Tony_9410
Author-email: tony_9410@foxmail.com
Project-URL: Homepage, https://github.com/yang445786754/call_function_with_timeout
Classifier: Programming Language :: Python :: 3
Classifier: License :: OSI Approved :: MIT License
Classifier: Operating System :: OS Independent
Requires-Python: >=3.6
License-File: LICENSE
